terencePDF/__init__.py
terencePDF/pdf2image.py
terencePDF/pdf2text.py
terencePDF-1.0.dist-info/LICENSE
terencePDF-1.0.dist-info/METADATA
terencePDF-1.0.dist-info/WHEEL
terencePDF-1.0.dist-info/top_level.txt
terencePDF-1.0.dist-info/RECORD
